{
  "d": {
    "__count": "1",
    "results": [
      {
        "Exams": {
          "results": []
        },
        "Name": "נושאים נבחרים בהנדסת נתונים ומידע",
        "OrgText": "הפקולטה למדעי הנתונים וההחלטות",
        "Otjid": "SM00960290",
        "Points": "2.50000",
        "Responsible": {
          "results": [
            {
              "Events": {
                "__deferred": {
                  "uri": "https://portalex.technion.ac.il:443/sap/opu/odata/sap/Z_CM_EV_CDIR_DATA_SRV/PObjectSet(Otjid='P%2000060436',Peryr='2021',Perid='200',ZzExamFunction='')/Events"
                }
              },
              "FirstName": "שלומי",
              "LastName": "לויפר",
              "OrgId": "00002190",
              "OrgText": "הפקולטה להנדסת תעשייה וניהול",
              "OrgUrl": "",
              "Otjid": "P 00060436",
              "Perid": "200",
              "Peryr": "2021",
              "Responsible": {
                "__deferred": {
                  "uri": "https://portalex.technion.ac.il:443/sap/opu/odata/sap/Z_CM_EV_CDIR_DATA_SRV/PObjectSet(Otjid='P%2000060436',Peryr='2021',Perid='200',ZzExamFunction='')/Responsible"
                }
              },
              "Seark": "",
              "Title": "ד\"ר",
              "ZzContactUrl": "",
              "ZzExamFunction": "",
              "ZzExamFunctionText": "",
              "__metadata": {
                "id": "https://portalex.technion.ac.il:443/sap/opu/odata/sap/Z_CM_EV_CDIR_DATA_SRV/PObjectSet(Otjid='P%2000060436',Peryr='2021',Perid='200',ZzExamFunction='')",
                "type": "NVIAS_CDIR_DATA_SRV.PObject",
                "uri": "https://portalex.technion.ac.il:443/sap/opu/odata/sap/Z_CM_EV_CDIR_DATA_SRV/PObjectSet(Otjid='P%2000060436',Peryr='2021',Perid='200',ZzExamFunction='')"
              }
            }
          ]
        },
        "SmPrereq": {
          "results": []
        },
        "SmRelations": {
          "results": []
        },
        "StudyContentDescription": "נושאים נבחרים ובעיות מאתגרות בהן מתמקד המחקר בהנדסת נתונים ומידע אשר אינם נלמדים בקורסים האחרים. הקורס יוקדש בכל סמסטר לנושא אחר. תוצאות למידה: בסיום הקורס הסטודנט ייחשף לנושאי מחקר שונים בהנדסת נתונים ומידע או להתמודדות עם סוג נתונים שונה. הערה: סילבוס מפורט יוגש לאישור ביה\"ס כתנאי לפתיחת הקורס בכל סמסטר. סמסטר א' תשע\"ט: שילוב נתונים בסביבת אי ודאות. סמסטר א' תש\"פ: שיטות חיזוי בפיננסים. סמסטר א' תשפ\"א: שיטות להסבר מודלים והחלטות בבינה מלאכותית ולמידת מכונה.",
        "ZzAcademicLevel": "0002",
        "ZzAcademicLevelText": "מקצוע משותף",
        "ZzSemesterNote": "",
        "__metadata": {
          "id": "https://portalex.technion.ac.il:443/sap/opu/odata/sap/Z_CM_EV_CDIR_DATA_SRV/SmObjectSet(Otjid='SM00960290',Peryr='2021',Perid='200',ZzCgOtjid='',ZzPoVersion='',ZzScOtjid='')",
          "type": "NVIAS_CDIR_DATA_SRV.SmObject",
          "uri": "https://portalex.technion.ac.il:443/sap/opu/odata/sap/Z_CM_EV_CDIR_DATA_SRV/SmObjectSet(Otjid='SM00960290',Peryr='2021',Perid='200',ZzCgOtjid='',ZzPoVersion='',ZzScOtjid='')"
        }
      }
    ]
  }
}