{
  "d": {
    "__count": "1",
    "results": [
      {
        "Exams": {
          "results": []
        },
        "Name": "פיזיקה והתקנים של תחמוצות",
        "OrgText": "הפקולטה להנדסת חשמל ומחשבים",
        "Otjid": "SM00480812",
        "Points": "2.00000",
        "Responsible": {
          "results": []
        },
        "SmPrereq": {
          "results": []
        },
        "SmRelations": {
          "results": []
        },
        "StudyContentDescription": "הקורס סוקר יישומים עכשוויים של תחמוצות במיקרואלקטרוניקה, בדגש על חומרים בעלי מקדם דיאלקטרי גבוה בטרנזיסטורים. משם הקורס ממשיך לתיאור הפיזיקה והיישומים של תחמוצות פונקציונליות בעלות קורלציה אלקטרונית. הקורס משלב היבטים של הפיזיקה מאחורי התכונות האלקטרוניות המיוחדות של התחמוצות עם היבטים פרקטיים של גידול השכבות, ודוגמאות להתקנים אלקטרוניים.              \r\n תוצאות למידה: עם השלמת הקורס לסטודנט תהיה היכרות רחבה עם תחמוצות כחומרים אלקטרונים, ויישומיהן בהתקנים נוכחיים ועתידיים. הסטודנט יהיה מסוגל להסביר את הקשר בין תכונות החומר (מבנה אטומי, הרכב) למבנה האלקטרוני במספר דוגמאות מייצגות, וידע לנתח את הפיזיק ה שמאחוריהן. לבוגר הקורס תהיה יכולת להסביר את השימושיות של תחמוצות בהתקנים עתידיים.                     \r\n",
        "ZzAcademicLevel": "0003",
        "ZzAcademicLevelText": "תארים מתקדמים",
        "ZzSemesterNote": "",
        "__metadata": {
          "id": "https://portalex.technion.ac.il:443/sap/opu/odata/sap/Z_CM_EV_CDIR_DATA_SRV/SmObjectSet(Otjid='SM00480812',Peryr='2021',Perid='200',ZzCgOtjid='',ZzPoVersion='',ZzScOtjid='')",
          "type": "NVIAS_CDIR_DATA_SRV.SmObject",
          "uri": "https://portalex.technion.ac.il:443/sap/opu/odata/sap/Z_CM_EV_CDIR_DATA_SRV/SmObjectSet(Otjid='SM00480812',Peryr='2021',Perid='200',ZzCgOtjid='',ZzPoVersion='',ZzScOtjid='')"
        }
      }
    ]
  }
}