{
  "d": {
    "__count": "1",
    "results": [
      {
        "Exams": {
          "results": [
            {
              "Category": "מבחן מועד א",
              "CategoryCode": "FI",
              "DregDateEnd": "                                                                                                                                                                                                                                                                                                                                                                                                                                                                                                                                                                                                                                                                                                                                                                                                                                                                                                                                                                                                                                                                                                                                                                                                                                              0",
              "DregDateStart": "0",
              "ExamBegTime": "PT13H00M00S",
              "ExamDate": "/Date(1771113600000)/",
              "ExamEndTime": "PT16H00M00S",
              "ExamType": "מבחן בכתב",
              "Name": "מבחן מועד א 00140890",
              "OfferNo": "001",
              "Otjid": "CE00035536",
              "Perid": "200",
              "Person": "",
              "PersonOtjid": "",
              "Persons": {
                "__deferred": {
                  "uri": "https://portalex.technion.ac.il:443/sap/opu/odata/sap/Z_CM_EV_CDIR_DATA_SRV/CeObjectSet(Otjid='CE00035536',Peryr='2025',Perid='200',OfferNo='001')/Persons"
                }
              },
              "Peryr": "2025",
              "Points": "4.00000",
              "PointsMaximum": "4.00000",
              "PointsMinimum": "4.00000",
              "RegisDateEnd": "0",
              "RegisDateStart": "0",
              "RoomName": "",
              "RoomOtjid": "G 00000000",
              "Seark": "",
              "Short": "מב1_00140890",
              "Unit": "CP",
              "ZzApprovedTools": "",
              "ZzDName": "",
              "ZzDOtjid": "",
              "ZzExamOfferGuid": "005056B8E2331FD093EA0D193ABA79F5",
              "ZzExamOfferParentGuid": "",
              "ZzExclusiveExtraTimeSt": "",
              "ZzExclusiveExtraTimeStT": "לסטודנטים ללא תוספת זמן",
              "ZzHeldDigital": false,
              "ZzOnlineRegPossible": false,
              "ZzSeComment": "",
              "ZzSmName": "מבוא לספקטרוסקופיה וחישה מרחוק",
              "ZzSmOtjid": "SM00140890",
              "ZzSmShort": "מק-00140890",
              "__metadata": {
                "id": "https://portalex.technion.ac.il:443/sap/opu/odata/sap/Z_CM_EV_CDIR_DATA_SRV/CeObjectSet(Otjid='CE00035536',Peryr='2025',Perid='200',OfferNo='001')",
                "type": "NVIAS_CDIR_DATA_SRV.CeObject",
                "uri": "https://portalex.technion.ac.il:443/sap/opu/odata/sap/Z_CM_EV_CDIR_DATA_SRV/CeObjectSet(Otjid='CE00035536',Peryr='2025',Perid='200',OfferNo='001')"
              }
            },
            {
              "Category": "מבחן מועד א",
              "CategoryCode": "FI",
              "DregDateEnd": "                                                                                                                                                                                                                                                                                                                                                                                                                                                                                                                                                                                                                                                                                                                                                                                                                                                                                                                                                                                                                                                                                                                                                                                                                                              0",
              "DregDateStart": "0",
              "ExamBegTime": "PT13H00M00S",
              "ExamDate": "/Date(1771113600000)/",
              "ExamEndTime": "PT16H00M00S",
              "ExamType": "מבחן בכתב",
              "Name": "מבחן מועד א 00140890",
              "OfferNo": "002",
              "Otjid": "CE00035536",
              "Perid": "200",
              "Person": "",
              "PersonOtjid": "",
              "Persons": {
                "__deferred": {
                  "uri": "https://portalex.technion.ac.il:443/sap/opu/odata/sap/Z_CM_EV_CDIR_DATA_SRV/CeObjectSet(Otjid='CE00035536',Peryr='2025',Perid='200',OfferNo='002')/Persons"
                }
              },
              "Peryr": "2025",
              "Points": "4.00000",
              "PointsMaximum": "4.00000",
              "PointsMinimum": "4.00000",
              "RegisDateEnd": "0",
              "RegisDateStart": "0",
              "RoomName": "020-0302",
              "RoomOtjid": "G 00200302",
              "Seark": "",
              "Short": "מב1_00140890",
              "Unit": "CP",
              "ZzApprovedTools": "",
              "ZzDName": "",
              "ZzDOtjid": "",
              "ZzExamOfferGuid": "005056B8E2331FD0B3D56AB1F163BA05",
              "ZzExamOfferParentGuid": "005056B8E2331FD093EA0D193ABA79F5",
              "ZzExclusiveExtraTimeSt": "M",
              "ZzExclusiveExtraTimeStT": "לסטודנטים עם תוספת זמן /וללא תוספת זמן",
              "ZzHeldDigital": false,
              "ZzOnlineRegPossible": false,
              "ZzSeComment": "",
              "ZzSmName": "מבוא לספקטרוסקופיה וחישה מרחוק",
              "ZzSmOtjid": "SM00140890",
              "ZzSmShort": "מק-00140890",
              "__metadata": {
                "id": "https://portalex.technion.ac.il:443/sap/opu/odata/sap/Z_CM_EV_CDIR_DATA_SRV/CeObjectSet(Otjid='CE00035536',Peryr='2025',Perid='200',OfferNo='002')",
                "type": "NVIAS_CDIR_DATA_SRV.CeObject",
                "uri": "https://portalex.technion.ac.il:443/sap/opu/odata/sap/Z_CM_EV_CDIR_DATA_SRV/CeObjectSet(Otjid='CE00035536',Peryr='2025',Perid='200',OfferNo='002')"
              }
            },
            {
              "Category": "מבחן מועד ב",
              "CategoryCode": "FB",
              "DregDateEnd": "                                                                                                                                                                                                                                                                                                                                                                                                                                                                                                                                                                                                                                                                                                                                                                                                                                                                                                                                                                                                                                                                                                                                                                                                                                 20260311235959",
              "DregDateStart": "20260201000000",
              "ExamBegTime": "PT09H00M00S",
              "ExamDate": "/Date(1773705600000)/",
              "ExamEndTime": "PT12H00M00S",
              "ExamType": "מבחן בכתב",
              "Name": "מבחן מועד ב 00140890",
              "OfferNo": "001",
              "Otjid": "CE00033000",
              "Perid": "200",
              "Person": "",
              "PersonOtjid": "",
              "Persons": {
                "__deferred": {
                  "uri": "https://portalex.technion.ac.il:443/sap/opu/odata/sap/Z_CM_EV_CDIR_DATA_SRV/CeObjectSet(Otjid='CE00033000',Peryr='2025',Perid='200',OfferNo='001')/Persons"
                }
              },
              "Peryr": "2025",
              "Points": "4.00000",
              "PointsMaximum": "4.00000",
              "PointsMinimum": "4.00000",
              "RegisDateEnd": "20260311235959",
              "RegisDateStart": "20260201000000",
              "RoomName": "",
              "RoomOtjid": "G 00000000",
              "Seark": "",
              "Short": "מב2_00140890",
              "Unit": "CP",
              "ZzApprovedTools": "",
              "ZzDName": "",
              "ZzDOtjid": "",
              "ZzExamOfferGuid": "005056B8E2331FD0949D59C3D16A59F5",
              "ZzExamOfferParentGuid": "",
              "ZzExclusiveExtraTimeSt": "",
              "ZzExclusiveExtraTimeStT": "לסטודנטים ללא תוספת זמן",
              "ZzHeldDigital": false,
              "ZzOnlineRegPossible": true,
              "ZzSeComment": "",
              "ZzSmName": "מבוא לספקטרוסקופיה וחישה מרחוק",
              "ZzSmOtjid": "SM00140890",
              "ZzSmShort": "מק-00140890",
              "__metadata": {
                "id": "https://portalex.technion.ac.il:443/sap/opu/odata/sap/Z_CM_EV_CDIR_DATA_SRV/CeObjectSet(Otjid='CE00033000',Peryr='2025',Perid='200',OfferNo='001')",
                "type": "NVIAS_CDIR_DATA_SRV.CeObject",
                "uri": "https://portalex.technion.ac.il:443/sap/opu/odata/sap/Z_CM_EV_CDIR_DATA_SRV/CeObjectSet(Otjid='CE00033000',Peryr='2025',Perid='200',OfferNo='001')"
              }
            },
            {
              "Category": "מבחן מועד ב",
              "CategoryCode": "FB",
              "DregDateEnd": "                                                                                                                                                                                                                                                                                                                                                                                                                                                                                                                                                                                                                                                                                                                                                                                                                                                                                                                                                                                                                                                                                                                                                                                                                                 20260311000000",
              "DregDateStart": "20260201000000",
              "ExamBegTime": "PT09H00M00S",
              "ExamDate": "/Date(1773705600000)/",
              "ExamEndTime": "PT12H00M00S",
              "ExamType": "מבחן בכתב",
              "Name": "מבחן מועד ב 00140890",
              "OfferNo": "002",
              "Otjid": "CE00033000",
              "Perid": "200",
              "Person": "",
              "PersonOtjid": "",
              "Persons": {
                "__deferred": {
                  "uri": "https://portalex.technion.ac.il:443/sap/opu/odata/sap/Z_CM_EV_CDIR_DATA_SRV/CeObjectSet(Otjid='CE00033000',Peryr='2025',Perid='200',OfferNo='002')/Persons"
                }
              },
              "Peryr": "2025",
              "Points": "4.00000",
              "PointsMaximum": "4.00000",
              "PointsMinimum": "4.00000",
              "RegisDateEnd": "20260311000000",
              "RegisDateStart": "20260201000000",
              "RoomName": "020-0507",
              "RoomOtjid": "G 00200507",
              "Seark": "",
              "Short": "מב2_00140890",
              "Unit": "CP",
              "ZzApprovedTools": "",
              "ZzDName": "",
              "ZzDOtjid": "",
              "ZzExamOfferGuid": "005056B8E2331FD0B7FCBE98308C3A09",
              "ZzExamOfferParentGuid": "005056B8E2331FD0949D59C3D16A59F5",
              "ZzExclusiveExtraTimeSt": "M",
              "ZzExclusiveExtraTimeStT": "לסטודנטים עם תוספת זמן /וללא תוספת זמן",
              "ZzHeldDigital": false,
              "ZzOnlineRegPossible": true,
              "ZzSeComment": "",
              "ZzSmName": "מבוא לספקטרוסקופיה וחישה מרחוק",
              "ZzSmOtjid": "SM00140890",
              "ZzSmShort": "מק-00140890",
              "__metadata": {
                "id": "https://portalex.technion.ac.il:443/sap/opu/odata/sap/Z_CM_EV_CDIR_DATA_SRV/CeObjectSet(Otjid='CE00033000',Peryr='2025',Perid='200',OfferNo='002')",
                "type": "NVIAS_CDIR_DATA_SRV.CeObject",
                "uri": "https://portalex.technion.ac.il:443/sap/opu/odata/sap/Z_CM_EV_CDIR_DATA_SRV/CeObjectSet(Otjid='CE00033000',Peryr='2025',Perid='200',OfferNo='002')"
              }
            }
          ]
        },
        "Name": "מבוא לספקטרוסקופיה וחישה מרחוק",
        "OrgText": "הפקולטה להנדסה אזרחית וסביבתית",
        "Otjid": "SM00140890",
        "Points": "4.00000",
        "Responsible": {
          "results": [
            {
              "Events": {
                "__deferred": {
                  "uri": "https://portalex.technion.ac.il:443/sap/opu/odata/sap/Z_CM_EV_CDIR_DATA_SRV/PObjectSet(Otjid='P%2000050813',Peryr='2025',Perid='200',ZzExamFunction='')/Events"
                }
              },
              "FirstName": "פאדי",
              "LastName": "קיזל",
              "OrgId": "00002010",
              "OrgText": "הפקולטה להנדסה אזרחית וסביבתית",
              "OrgUrl": "https://ugportal.technion.ac.il/wp-content/uploads/2024/02/01-%D7%94%D7%A0%D7%93%D7%A1%D7%94-%D7%90%",
              "Otjid": "P 00050813",
              "Perid": "200",
              "Peryr": "2025",
              "Responsible": {
                "__deferred": {
                  "uri": "https://portalex.technion.ac.il:443/sap/opu/odata/sap/Z_CM_EV_CDIR_DATA_SRV/PObjectSet(Otjid='P%2000050813',Peryr='2025',Perid='200',ZzExamFunction='')/Responsible"
                }
              },
              "Seark": "",
              "Title": "פרופ\"ח",
              "ZzContactUrl": "",
              "ZzExamFunction": "",
              "ZzExamFunctionText": "",
              "__metadata": {
                "id": "https://portalex.technion.ac.il:443/sap/opu/odata/sap/Z_CM_EV_CDIR_DATA_SRV/PObjectSet(Otjid='P%2000050813',Peryr='2025',Perid='200',ZzExamFunction='')",
                "type": "NVIAS_CDIR_DATA_SRV.PObject",
                "uri": "https://portalex.technion.ac.il:443/sap/opu/odata/sap/Z_CM_EV_CDIR_DATA_SRV/PObjectSet(Otjid='P%2000050813',Peryr='2025',Perid='200',ZzExamFunction='')"
              }
            }
          ]
        },
        "SmPrereq": {
          "results": [
            {
              "Bracket": "(",
              "DependentModuleId": "00140890",
              "LineNumber": "001",
              "ModuleId": "00140877",
              "ModuleName": "כרטוגרפיה ומבוא לממ\"ג",
              "ModuleShort": "מק-00140877",
              "Operator": "",
              "Perid": "000",
              "Peryr": "0000",
              "__metadata": {
                "id": "https://portalex.technion.ac.il:443/sap/opu/odata/sap/Z_CM_EV_CDIR_DATA_SRV/SmPrerequisitesSet(DependentModuleId='00140890',LineNumber='001')",
                "type": "NVIAS_CDIR_DATA_SRV.SmPrerequisites",
                "uri": "https://portalex.technion.ac.il:443/sap/opu/odata/sap/Z_CM_EV_CDIR_DATA_SRV/SmPrerequisitesSet(DependentModuleId='00140890',LineNumber='001')"
              }
            },
            {
              "Bracket": ")",
              "DependentModuleId": "00140890",
              "LineNumber": "002",
              "ModuleId": "00000000",
              "ModuleName": "",
              "ModuleShort": "",
              "Operator": "OR",
              "Perid": "000",
              "Peryr": "0000",
              "__metadata": {
                "id": "https://portalex.technion.ac.il:443/sap/opu/odata/sap/Z_CM_EV_CDIR_DATA_SRV/SmPrerequisitesSet(DependentModuleId='00140890',LineNumber='002')",
                "type": "NVIAS_CDIR_DATA_SRV.SmPrerequisites",
                "uri": "https://portalex.technion.ac.il:443/sap/opu/odata/sap/Z_CM_EV_CDIR_DATA_SRV/SmPrerequisitesSet(DependentModuleId='00140890',LineNumber='002')"
              }
            },
            {
              "Bracket": "(",
              "DependentModuleId": "00140890",
              "LineNumber": "003",
              "ModuleId": "00140405",
              "ModuleName": "גיאולוגיה הנדסית",
              "ModuleShort": "מק-00140405",
              "Operator": "",
              "Perid": "000",
              "Peryr": "0000",
              "__metadata": {
                "id": "https://portalex.technion.ac.il:443/sap/opu/odata/sap/Z_CM_EV_CDIR_DATA_SRV/SmPrerequisitesSet(DependentModuleId='00140890',LineNumber='003')",
                "type": "NVIAS_CDIR_DATA_SRV.SmPrerequisites",
                "uri": "https://portalex.technion.ac.il:443/sap/opu/odata/sap/Z_CM_EV_CDIR_DATA_SRV/SmPrerequisitesSet(DependentModuleId='00140890',LineNumber='003')"
              }
            },
            {
              "Bracket": ")",
              "DependentModuleId": "00140890",
              "LineNumber": "004",
              "ModuleId": "00000000",
              "ModuleName": "",
              "ModuleShort": "",
              "Operator": "OR",
              "Perid": "000",
              "Peryr": "0000",
              "__metadata": {
                "id": "https://portalex.technion.ac.il:443/sap/opu/odata/sap/Z_CM_EV_CDIR_DATA_SRV/SmPrerequisitesSet(DependentModuleId='00140890',LineNumber='004')",
                "type": "NVIAS_CDIR_DATA_SRV.SmPrerequisites",
                "uri": "https://portalex.technion.ac.il:443/sap/opu/odata/sap/Z_CM_EV_CDIR_DATA_SRV/SmPrerequisitesSet(DependentModuleId='00140890',LineNumber='004')"
              }
            },
            {
              "Bracket": "(",
              "DependentModuleId": "00140890",
              "LineNumber": "005",
              "ModuleId": "00140968",
              "ModuleName": "אקולוגיה למהנדסים",
              "ModuleShort": "מק-00140968",
              "Operator": "",
              "Perid": "000",
              "Peryr": "0000",
              "__metadata": {
                "id": "https://portalex.technion.ac.il:443/sap/opu/odata/sap/Z_CM_EV_CDIR_DATA_SRV/SmPrerequisitesSet(DependentModuleId='00140890',LineNumber='005')",
                "type": "NVIAS_CDIR_DATA_SRV.SmPrerequisites",
                "uri": "https://portalex.technion.ac.il:443/sap/opu/odata/sap/Z_CM_EV_CDIR_DATA_SRV/SmPrerequisitesSet(DependentModuleId='00140890',LineNumber='005')"
              }
            },
            {
              "Bracket": ")",
              "DependentModuleId": "00140890",
              "LineNumber": "006",
              "ModuleId": "00000000",
              "ModuleName": "",
              "ModuleShort": "",
              "Operator": "",
              "Perid": "000",
              "Peryr": "0000",
              "__metadata": {
                "id": "https://portalex.technion.ac.il:443/sap/opu/odata/sap/Z_CM_EV_CDIR_DATA_SRV/SmPrerequisitesSet(DependentModuleId='00140890',LineNumber='006')",
                "type": "NVIAS_CDIR_DATA_SRV.SmPrerequisites",
                "uri": "https://portalex.technion.ac.il:443/sap/opu/odata/sap/Z_CM_EV_CDIR_DATA_SRV/SmPrerequisitesSet(DependentModuleId='00140890',LineNumber='006')"
              }
            }
          ]
        },
        "SmRelations": {
          "results": [
            {
              "Achievements": {
                "__deferred": {
                  "uri": "https://portalex.technion.ac.il:443/sap/opu/odata/sap/Z_CM_EV_CDIR_DATA_SRV/SmObjectSet(Otjid='SM00140874',Peryr='0000',Perid='000',ZzCgOtjid='',ZzPoVersion='',ZzScOtjid='')/Achievements"
                }
              },
              "Category": "",
              "CategoryText": "",
              "CreditsPrereqsDescription": "",
              "CreditsPrereqsHeadline": "",
              "Descr": "",
              "Events": {
                "__deferred": {
                  "uri": "https://portalex.technion.ac.il:443/sap/opu/odata/sap/Z_CM_EV_CDIR_DATA_SRV/SmObjectSet(Otjid='SM00140874',Peryr='0000',Perid='000',ZzCgOtjid='',ZzPoVersion='',ZzScOtjid='')/Events"
                }
              },
              "Exams": {
                "__deferred": {
                  "uri": "https://portalex.technion.ac.il:443/sap/opu/odata/sap/Z_CM_EV_CDIR_DATA_SRV/SmObjectSet(Otjid='SM00140874',Peryr='0000',Perid='000',ZzCgOtjid='',ZzPoVersion='',ZzScOtjid='')/Exams"
                }
              },
              "IgnoreFilterFlag": false,
              "ModuleChoicesDescription": "",
              "ModuleChoicesHeadline": "",
              "Name": "מבוא לחישה מרחוק",
              "ObjectiveDescription": "",
              "ObjectiveHeadline": "",
              "OrgId": "00000000",
              "OrgText": "",
              "Organizations": {
                "__deferred": {
                  "uri": "https://portalex.technion.ac.il:443/sap/opu/odata/sap/Z_CM_EV_CDIR_DATA_SRV/SmObjectSet(Otjid='SM00140874',Peryr='0000',Perid='000',ZzCgOtjid='',ZzPoVersion='',ZzScOtjid='')/Organizations"
                }
              },
              "Otjid": "SM00140874",
              "Partof": {
                "__deferred": {
                  "uri": "https://portalex.technion.ac.il:443/sap/opu/odata/sap/Z_CM_EV_CDIR_DATA_SRV/SmObjectSet(Otjid='SM00140874',Peryr='0000',Perid='000',ZzCgOtjid='',ZzPoVersion='',ZzScOtjid='')/Partof"
                }
              },
              "Perid": "000",
              "Peryr": "0000",
              "Points": "0.00000",
              "PointsMaximum": "0.00000",
              "PointsMinimum": "0.00000",
              "Responsible": {
                "__deferred": {
                  "uri": "https://portalex.technion.ac.il:443/sap/opu/odata/sap/Z_CM_EV_CDIR_DATA_SRV/SmObjectSet(Otjid='SM00140874',Peryr='0000',Perid='000',ZzCgOtjid='',ZzPoVersion='',ZzScOtjid='')/Responsible"
                }
              },
              "ScaleDescription": "",
              "ScaleId": "",
              "SeObjectSet": {
                "__deferred": {
                  "uri": "https://portalex.technion.ac.il:443/sap/opu/odata/sap/Z_CM_EV_CDIR_DATA_SRV/SmObjectSet(Otjid='SM00140874',Peryr='0000',Perid='000',ZzCgOtjid='',ZzPoVersion='',ZzScOtjid='')/SeObjectSet"
                }
              },
              "Seark": "",
              "Short": "מק-00140874",
              "SmOfferedPeriodSet": {
                "__deferred": {
                  "uri": "https://portalex.technion.ac.il:443/sap/opu/odata/sap/Z_CM_EV_CDIR_DATA_SRV/SmObjectSet(Otjid='SM00140874',Peryr='0000',Perid='000',ZzCgOtjid='',ZzPoVersion='',ZzScOtjid='')/SmOfferedPeriodSet"
                }
              },
              "SmPrereq": {
                "__deferred": {
                  "uri": "https://portalex.technion.ac.il:443/sap/opu/odata/sap/Z_CM_EV_CDIR_DATA_SRV/SmObjectSet(Otjid='SM00140874',Peryr='0000',Perid='000',ZzCgOtjid='',ZzPoVersion='',ZzScOtjid='')/SmPrereq"
                }
              },
              "SmRelations": {
                "__deferred": {
                  "uri": "https://portalex.technion.ac.il:443/sap/opu/odata/sap/Z_CM_EV_CDIR_DATA_SRV/SmObjectSet(Otjid='SM00140874',Peryr='0000',Perid='000',ZzCgOtjid='',ZzPoVersion='',ZzScOtjid='')/SmRelations"
                }
              },
              "SmRelationsReverse": {
                "__deferred": {
                  "uri": "https://portalex.technion.ac.il:443/sap/opu/odata/sap/Z_CM_EV_CDIR_DATA_SRV/SmObjectSet(Otjid='SM00140874',Peryr='0000',Perid='000',ZzCgOtjid='',ZzPoVersion='',ZzScOtjid='')/SmRelationsReverse"
                }
              },
              "StudyContentDescription": "",
              "StudyContentHeadline": "",
              "Unit": "",
              "WeeklyHours": {
                "__deferred": {
                  "uri": "https://portalex.technion.ac.il:443/sap/opu/odata/sap/Z_CM_EV_CDIR_DATA_SRV/SmObjectSet(Otjid='SM00140874',Peryr='0000',Perid='000',ZzCgOtjid='',ZzPoVersion='',ZzScOtjid='')/WeeklyHours"
                }
              },
              "ZzAcademicLevel": "0000",
              "ZzAcademicLevelText": "",
              "ZzCgOtjid": "",
              "ZzMaxRecommendedPerid": "0000",
              "ZzMinRecommendedPerid": "0000",
              "ZzOfferpattern": "",
              "ZzOfferpatternText": "",
              "ZzPersonalized": false,
              "ZzPoVersion": "",
              "ZzRecommendedPeridUnit": "0000",
              "ZzRelationship": "אין קרדיט נוסף",
              "ZzRelationshipKey": "AZEC",
              "ZzScOtjid": "",
              "ZzSemesterNote": "",
              "ZzSemesterNoteLabel": "",
              "ZzSmLanguage": "",
              "ZzSmLanguageText": "",
              "__metadata": {
                "id": "https://portalex.technion.ac.il:443/sap/opu/odata/sap/Z_CM_EV_CDIR_DATA_SRV/SmObjectSet(Otjid='SM00140874',Peryr='0000',Perid='000',ZzCgOtjid='',ZzPoVersion='',ZzScOtjid='')",
                "type": "NVIAS_CDIR_DATA_SRV.SmObject",
                "uri": "https://portalex.technion.ac.il:443/sap/opu/odata/sap/Z_CM_EV_CDIR_DATA_SRV/SmObjectSet(Otjid='SM00140874',Peryr='0000',Perid='000',ZzCgOtjid='',ZzPoVersion='',ZzScOtjid='')"
              }
            }
          ]
        },
        "StudyContentDescription": "מטרות הקורס הם לימוד העקרונות הפיזיקליים של החישה מרחוק ופיתוח מיומנויות ליצירת  מפה מתמונה ספקטרלית. הנושאים שילמדו כוללים : אינטראקציה של קרינה עם חלקיקי חומר , העברה, בליעה, החזרה, השפעת אטמוספירה, חוק למברט, פיזור נפחי, ראדיאנס, החזרה ספקטרלית  מעלים ומקרקע, אינדקסים ספקטרליים, עירובים ספקטרליים, סיווג ספקטרלי, מערכות חישה.",
        "ZzAcademicLevel": "0001",
        "ZzAcademicLevelText": "לימודי הסמכה",
        "ZzSemesterNote": "",
        "__metadata": {
          "id": "https://portalex.technion.ac.il:443/sap/opu/odata/sap/Z_CM_EV_CDIR_DATA_SRV/SmObjectSet(Otjid='SM00140890',Peryr='2025',Perid='200',ZzCgOtjid='',ZzPoVersion='',ZzScOtjid='')",
          "type": "NVIAS_CDIR_DATA_SRV.SmObject",
          "uri": "https://portalex.technion.ac.il:443/sap/opu/odata/sap/Z_CM_EV_CDIR_DATA_SRV/SmObjectSet(Otjid='SM00140890',Peryr='2025',Perid='200',ZzCgOtjid='',ZzPoVersion='',ZzScOtjid='')"
        }
      }
    ]
  }
}