{
  "d": {
    "__count": "1",
    "results": [
      {
        "Exams": {
          "results": []
        },
        "Name": "פרויקט באינטרנט של הדברים",
        "OrgText": "הפקולטה למדעי המחשב",
        "Otjid": "SM02360333",
        "Points": "3.00000",
        "Responsible": {
          "results": [
            {
              "Events": {
                "__deferred": {
                  "uri": "https://portalex.technion.ac.il:443/sap/opu/odata/sap/Z_CM_EV_CDIR_DATA_SRV/PObjectSet(Otjid='P%2000011712',Peryr='2021',Perid='200',ZzExamFunction='')/Events"
                }
              },
              "FirstName": "ערן",
              "LastName": "יהב",
              "OrgId": "00002120",
              "OrgText": "הפקולטה למדעי המחשב",
              "OrgUrl": "",
              "Otjid": "P 00011712",
              "Perid": "200",
              "Peryr": "2021",
              "Responsible": {
                "__deferred": {
                  "uri": "https://portalex.technion.ac.il:443/sap/opu/odata/sap/Z_CM_EV_CDIR_DATA_SRV/PObjectSet(Otjid='P%2000011712',Peryr='2021',Perid='200',ZzExamFunction='')/Responsible"
                }
              },
              "Seark": "",
              "Title": "פרופ'",
              "ZzContactUrl": "",
              "ZzExamFunction": "",
              "ZzExamFunctionText": "",
              "__metadata": {
                "id": "https://portalex.technion.ac.il:443/sap/opu/odata/sap/Z_CM_EV_CDIR_DATA_SRV/PObjectSet(Otjid='P%2000011712',Peryr='2021',Perid='200',ZzExamFunction='')",
                "type": "NVIAS_CDIR_DATA_SRV.PObject",
                "uri": "https://portalex.technion.ac.il:443/sap/opu/odata/sap/Z_CM_EV_CDIR_DATA_SRV/PObjectSet(Otjid='P%2000011712',Peryr='2021',Perid='200',ZzExamFunction='')"
              }
            }
          ]
        },
        "SmPrereq": {
          "results": []
        },
        "SmRelations": {
          "results": []
        },
        "StudyContentDescription": "במסגרת הפרויקט יפתחו הסטודנטים אב טיפוס למוצר TOI. מוצר זה משלב תכנות מבוסס שירותי ענן, טלפון חכם, מיקרו-בקרים וחומרות שונות. העבודה מתבצעת בקבוצות של 3-2 סטודנטים. בסיום הקורס מוצג מוצר ומוגש דו\"ח כתוב. תוצאות למידה: בסיום הקורס הסטודנט יהיה מסוגל: לתכנן ולבנות יישומי TOI משולבי חומרה ותוכנה המבוססים על בקרי ארדואינו ומשתמשים במחשוב עננים ובטלפון חכם.נדרש ללמוד קורס זה יחד עם הקורס 233632.",
        "ZzAcademicLevel": "0002",
        "ZzAcademicLevelText": "מקצוע משותף",
        "ZzSemesterNote": "",
        "__metadata": {
          "id": "https://portalex.technion.ac.il:443/sap/opu/odata/sap/Z_CM_EV_CDIR_DATA_SRV/SmObjectSet(Otjid='SM02360333',Peryr='2021',Perid='200',ZzCgOtjid='',ZzPoVersion='',ZzScOtjid='')",
          "type": "NVIAS_CDIR_DATA_SRV.SmObject",
          "uri": "https://portalex.technion.ac.il:443/sap/opu/odata/sap/Z_CM_EV_CDIR_DATA_SRV/SmObjectSet(Otjid='SM02360333',Peryr='2021',Perid='200',ZzCgOtjid='',ZzPoVersion='',ZzScOtjid='')"
        }
      }
    ]
  }
}